nichord/__init__.py
nichord/chord.py
nichord/combine.py
nichord/convert.py
nichord/coord_labeler.py
nichord/glassbrain.py
nichord/patch_RendererAgg.py
nichord/peak.py
nichord-0.3.3.dist-info/LICENSE.txt
nichord-0.3.3.dist-info/METADATA
nichord-0.3.3.dist-info/WHEEL
nichord-0.3.3.dist-info/top_level.txt
nichord-0.3.3.dist-info/RECORD
